resolver/__init__.py
resolver/rcmd.py
sceptre_cmd_resolver-2.0.0.dist-info/LICENSE
sceptre_cmd_resolver-2.0.0.dist-info/METADATA
sceptre_cmd_resolver-2.0.0.dist-info/WHEEL
sceptre_cmd_resolver-2.0.0.dist-info/entry_points.txt
sceptre_cmd_resolver-2.0.0.dist-info/top_level.txt
sceptre_cmd_resolver-2.0.0.dist-info/RECORD
