Metadata-Version: 2.1
Name: sceptre-cmd-resolver
Version: 2.0.0
Summary: Sceptre resolver to execute generic shell commands
Home-page: https://github.com/Sceptre/sceptre-resolver-cmd
Author: Luke Plausin
Author-email: sceptre@cloudreach.com
License: Apache2
Keywords: sceptre,sceptre-resolver
Platform: UNKNOWN
Classifier: Intended Audience :: Developers
Classifier: Natural Language :: English
Classifier: Environment :: Console
Classifier: Programming Language :: Python :: 3.7
Classifier: Programming Language :: Python :: 3.8
Classifier: Programming Language :: Python :: 3.9
Classifier: Programming Language :: Python :: 3.10
Requires-Dist: sceptre (>=4.0.1)
Provides-Extra: test
Requires-Dist: pytest (>=3.2) ; extra == 'test'
